feynman_path/__init__.py
feynman_path/__main__.py
feynman_path/command.py
feynman_path/diagram.py
feynman_path-0.2.0.dist-info/LICENSE.txt
feynman_path-0.2.0.dist-info/METADATA
feynman_path-0.2.0.dist-info/WHEEL
feynman_path-0.2.0.dist-info/entry_points.txt
feynman_path-0.2.0.dist-info/top_level.txt
feynman_path-0.2.0.dist-info/RECORD
