Metadata-Version: 2.1
Name: feynman-path
Version: 0.2.0
Summary: Visualization tool for the Feynman Path Sum applied to quantum circuits
Home-page: https://github.com/cduck/feynman_path
Download-URL: https://github.com/cduck/feynman_path/archive/0.2.0.tar.gz
Author: Casey Duckering
License: UNKNOWN
Keywords: quantum computing,feynman path,path sum,jupyter
Platform: UNKNOWN
Classifier: License :: OSI Approved :: MIT License
Classifier: Development Status :: 3 - Alpha
Classifier: Programming Language :: Python :: 3
Classifier: Framework :: IPython
Classifier: Framework :: Jupyter
License-File: LICENSE.txt
Requires-Dist: drawSvg (~=2.0)
Requires-Dist: latextools (~=0.5)
Requires-Dist: sympy (~=1.7)
